setup.py
helloWorldSpecialEdition.egg-info/PKG-INFO
helloWorldSpecialEdition.egg-info/SOURCES.txt
helloWorldSpecialEdition.egg-info/dependency_links.txt
helloWorldSpecialEdition.egg-info/top_level.txt
paquete/helloWorldSpecialEdition.py