Metadata-Version: 2.1
Name: helloWorldSpecialEdition
Version: 0.1
Summary: Este es el paquete más poderoso en todo pip
Author: Steven Guerrero
Author-email: imstevenguerrero@gmail.com
License: UNKNOWN
Platform: UNKNOWN
